websleuth/__init__.py
websleuth/__version_cli.py
websleuth/async_middleware.py
websleuth/async_scraper.py
websleuth/export.py
websleuth/middleware.py
websleuth/parser.py
websleuth/queue.py
websleuth/scraper.py
websleuth/shared_utils.py
websleuth/utils.py
websleuth-1.0.0.dist-info/licenses/LICENSE
websleuth-1.0.0.dist-info/METADATA
websleuth-1.0.0.dist-info/WHEEL
websleuth-1.0.0.dist-info/entry_points.txt
websleuth-1.0.0.dist-info/top_level.txt
websleuth-1.0.0.dist-info/RECORD
