Metadata-Version: 2.4
Name: websleuth
Version: 1.0.0
Summary: WebSleuth - A lightweight, extensible web scraping framework.
Author-email: Sooraj <soorajkknmd@gmail.com>
License: MIT
Project-URL: Homepage, https://github.com/soorajInsights/WebSleuth
Project-URL: Repository, https://github.com/soorajInsights/WebSleuth
Requires-Python: >=3.8
License-File: LICENSE
Requires-Dist: requests
Requires-Dist: beautifulsoup4
Requires-Dist: fake-useragent
Requires-Dist: lxml
Requires-Dist: aiofiles
Requires-Dist: xlsxwriter
Requires-Dist: aiohttp
Requires-Dist: openpyxl
Provides-Extra: dev
Requires-Dist: pytest; extra == "dev"
Requires-Dist: black; extra == "dev"
Requires-Dist: flake8; extra == "dev"
Requires-Dist: twine; extra == "dev"
Requires-Dist: build; extra == "dev"
Dynamic: license-file
